README.md
setup.py
volkswagen/__init__.py
volkswagen.egg-info/PKG-INFO
volkswagen.egg-info/SOURCES.txt
volkswagen.egg-info/dependency_links.txt
volkswagen.egg-info/top_level.txt