Metadata-Version: 1.1
Name: volkswagen
Version: 0.1.1
Summary: Detect when your tests run in a CI and make them pass
Home-page: https://github.com/L3viathan/pyvw
Author: L3viathan
Author-email: git@l3vi.de
License: UNKNOWN
Platform: UNKNOWN
Classifier: Programming Language :: Python :: 3
Classifier: Operating System :: OS Independent
Classifier: Environment :: Console
Classifier: Intended Audience :: Developers
